mcp_dice/__init__.py
mcp_dice/server.py
mcp_dice-0.1.2.dist-info/METADATA
mcp_dice-0.1.2.dist-info/WHEEL
mcp_dice-0.1.2.dist-info/entry_points.txt
mcp_dice-0.1.2.dist-info/licenses/LICENSE
mcp_dice-0.1.2.dist-info/RECORD
