Metadata-Version: 2.3
Name: mcp-dice
Version: 0.1.2
Summary: MCP server enabling LLMs to roll dice
Project-URL: Homepage, https://github.com/YourUsername/mcp-dice
Project-URL: Repository, https://github.com/YourUsername/mcp-dice
Project-URL: Bug Tracker, https://github.com/YourUsername/mcp-dice/issues
Author-email: Yamato Matsuoka <yamaton@gmail.com>
Requires-Python: >=3.10
Requires-Dist: mcp>=1.0.0
Requires-Dist: python-dotenv>=1.0.1
Provides-Extra: dev
Requires-Dist: pytest>=8.3.3; extra == 'dev'
